mcmcplot/__init__.py
mcmcplot/mcmatplot.py
mcmcplot/mcmcplot.py
mcmcplot/mcseaborn.py
mcmcplot/utilities.py
mcmcplot-1.0.1.dist-info/LICENSE
mcmcplot-1.0.1.dist-info/METADATA
mcmcplot-1.0.1.dist-info/WHEEL
mcmcplot-1.0.1.dist-info/top_level.txt
mcmcplot-1.0.1.dist-info/RECORD
