Metadata-Version: 2.1
Name: mcmcplot
Version: 1.0.1
Summary: A library to plot and analyze chains from mcmc simulations
Home-page: https://github.com/prmiles/mcmcplot
Author: Paul Miles
Author-email: prmiles@ncsu.edu
License: MIT
Download-URL: https://github.com/prmiles/mcmcplot
Platform: UNKNOWN
Classifier: License :: OSI Approved :: MIT License
Classifier: Natural Language :: English
Classifier: Operating System :: MacOS :: MacOS X
Classifier: Operating System :: POSIX :: Linux
Classifier: Programming Language :: Python :: 3.6
Classifier: Framework :: IPython
Classifier: Intended Audience :: Science/Research
Classifier: Topic :: Scientific/Engineering
Provides-Extra: docs
Provides-Extra: plotting
